hericendre/__init__.py
hericendre/model.py
hericendre/results.py
hericendre/units.py
hericendre-0.1.0.data/scripts/hericendre
hericendre-0.1.0.dist-info/METADATA
hericendre-0.1.0.dist-info/WHEEL
hericendre-0.1.0.dist-info/RECORD
