Metadata-Version: 2.1
Name: hericendre
Version: 0.1.0
Summary: A radioactive decay and fuel depletion code
Author-Email: Nicolas Linden <nicolas@nlinden.com>
Requires-Python: >=3.11
Requires-Dist: h5py>=3.13.0
Requires-Dist: numpy>=2.2.4
Requires-Dist: pint>=0.24.4
Requires-Dist: polars>=1.26.0
